earnings_analyzer/__init__.py
earnings_analyzer/analyzer.py
earnings_analyzer/api.py
earnings_analyzer/config.py
earnings_analyzer/display.py
earnings_analyzer/main.py
earnings_analyzer/analysis/__init__.py
earnings_analyzer/analysis/fool_scraper.py
earnings_analyzer/analysis/sentiment_analyzer.py
earnings_analyzer/data/__init__.py
earnings_analyzer/data/database.py
earnings_analyzer/data/financial_data_fetcher.py
earnings_analyzer/tests/test_analyzer.py
earnings_analyzer/tests/test_financial_data_fetcher.py
earnings_analyzer/tests/test_fool_scraper.py
earnings_analyzer/tests/test_new_features.py
earnings_analyzer/utils/__init__.py
earnings_analyzer-1.2.2.dist-info/METADATA
earnings_analyzer-1.2.2.dist-info/WHEEL
earnings_analyzer-1.2.2.dist-info/entry_points.txt
earnings_analyzer-1.2.2.dist-info/top_level.txt
earnings_analyzer-1.2.2.dist-info/RECORD
