Metadata-Version: 2.4
Name: earnings_analyzer
Version: 1.2.2
Summary: Fetch, analyze, and score earnings call transcripts with composable functions and database caching
Author-email: Jeremiah Bohr <jeremiah.bohr@gmail.com>
License: MIT
Project-URL: Homepage, https://github.com/jeremiahbohr/earnings-analyzer
Project-URL: Bug Tracker, https://github.com/jeremiahbohr/earnings-analyzer/issues
Classifier: Programming Language :: Python :: 3
Classifier: License :: OSI Approved :: MIT License
Classifier: Operating System :: OS Independent
Requires-Python: >=3.9
Requires-Dist: requests>=2.31.0
Requires-Dist: pandas>=2.0.0
Requires-Dist: google-generativeai>=0.3.0
Requires-Dist: python-dotenv>=1.0.0
Requires-Dist: scipy>=1.11.0
Requires-Dist: sec-api>=1.0.0
Requires-Dist: beautifulsoup4<5,>=4.12.3
Requires-Dist: lxml<6,>=5.2.2
Requires-Dist: googlesearch-python>=1.1.0
Provides-Extra: dev
Requires-Dist: pytest>=7.0; extra == "dev"
Requires-Dist: black; extra == "dev"
Requires-Dist: flake8; extra == "dev"
